pymqttusb/__init__.py
pymqttusb/main.py
pymqttusb-1.1.8.dist-info/LICENCE
pymqttusb-1.1.8.dist-info/METADATA
pymqttusb-1.1.8.dist-info/WHEEL
pymqttusb-1.1.8.dist-info/top_level.txt
pymqttusb-1.1.8.dist-info/RECORD
