Metadata-Version: 2.1
Name: pymqttusb
Version: 1.1.8
Summary: Connexion USB <-> MQTT ssl ou wss
Author: Didier Orlandi
Author-email: didier.orlandi@wanadoo.fr
Classifier: Programming Language :: Python :: 3
Classifier: License :: OSI Approved :: MIT License
Classifier: Operating System :: OS Independent
Requires-Python: >=3.4
License-File: LICENCE
Requires-Dist: paho-mqtt <2.0.0
Requires-Dist: mqtt-thread
Requires-Dist: pyserial >=3.5
